{"_meta": "after streaming and filtering, raw data: number of posts per subreddit per file", "RS_2005-06": {}, "RS_2023-10": {"wallstreetbets": 4578, "investing": 974, "stocks": 706}, "RS_2014-07": {"investing": 1624, "wallstreetbets": 156, "stocks": 554}, "RS_2018-09": {"wallstreetbets": 5365, "investing": 1349, "stocks": 1061}, "RS_2009-08": {"investing": 130, "stocks": 12}, "RS_2016-04": {"investing": 1284, "wallstreetbets": 2234, "stocks": 669}, "RS_2007-05": {}, "RS_2016-03": {"investing": 1261, "wallstreetbets": 1738, "stocks": 654}, "RS_2007-02": {}, "RS_2023-02": {"wallstreetbets": 6952, "investing": 557, "stocks": 599}, "RS_2023-05": {"wallstreetbets": 4216, "investing": 544, "stocks": 666}, "RS_2014-12": {"investing": 1698, "stocks": 767, "wallstreetbets": 144}, "RS_2010-08": {"stocks": 36, "investing": 99}, "RS_2021-01": {"wallstreetbets": 141638, "stocks": 3581, "investing": 1613}, "RS_2007-10": {}, "RS_2021-06": {"stocks": 1456, "wallstreetbets": 31798, "investing": 538}, "RS_2016-11": {"wallstreetbets": 2862, "stocks": 919, "investing": 1225}, "RS_2011-05": {"investing": 409, "stocks": 99}, "RS_2011-02": {"investing": 319, "stocks": 39}, "RS_2019-11": {"investing": 1417, "wallstreetbets": 3188, "stocks": 958}, "RS_2008-10": {"stocks": 9, "investing": 40}, "RS_2024-11": {"wallstreetbets": 7306, "investing": 1334, "stocks": 921}, "RS_2013-06": {"investing": 1124, "stocks": 269, "wallstreetbets": 63}, "RS_2013-01": {"investing": 1184, "stocks": 243, "wallstreetbets": 43}, "RS_2022-08": {"wallstreetbets": 20777, "stocks": 1001, "investing": 422}, "RS_2006-08": {}, "RS_2017-09": {"wallstreetbets": 2432, "investing": 1059, "stocks": 791}, "RS_2011-10": {"investing": 538, "stocks": 148}, "RS_2024-03": {"wallstreetbets": 13013, "investing": 1535, "stocks": 1097}, "RS_2008-02": {}, "RS_2019-03": {"wallstreetbets": 2546, "investing": 1533, "stocks": 834}, "RS_2008-05": {"investing": 1}, "RS_2024-04": {"investing": 1261, "wallstreetbets": 8756, "stocks": 963}, "RS_2019-04": {"investing": 1324, "stocks": 817, "wallstreetbets": 3378}, "RS_2005-12": {}, "RS_2023-04": {"wallstreetbets": 3723, "stocks": 574, "investing": 522}, "RS_2023-03": {"wallstreetbets": 7466, "stocks": 664, "investing": 709}, "RS_2016-10": {"investing": 959, "wallstreetbets": 2112, "stocks": 671}, "RS_2021-07": {"wallstreetbets": 10453, "stocks": 1213, "investing": 385}, "RS_2007-11": {}, "RS_2010-09": {"investing": 185, "stocks": 24}, "RS_2009-09": {"investing": 162, "stocks": 14}, "RS_2014-01": {"investing": 1714, "wallstreetbets": 228, "stocks": 1142}, "RS_2018-08": {"wallstreetbets": 6119, "investing": 1623, "stocks": 1148}, "RS_2014-06": {"wallstreetbets": 138, "investing": 1496, "stocks": 430}, "RS_2023-11": {"wallstreetbets": 5014, "investing": 987, "stocks": 758}, "RS_2005-07": {}, "RS_2007-03": {}, "RS_2016-02": {"wallstreetbets": 1473, "investing": 1532, "stocks": 591}, "RS_2007-04": {}, "RS_2016-05": {"investing": 1221, "wallstreetbets": 1761, "stocks": 723}, "RS_2021-12": {"wallstreetbets": 8614, "stocks": 1349, "investing": 262}, "RS_2011-11": {"investing": 814, "stocks": 151}, "RS_2017-08": {"investing": 1358, "wallstreetbets": 2595, "stocks": 1008}, "RS_2006-09": {}, "RS_2019-05": {"stocks": 945, "investing": 1244, "wallstreetbets": 3017}, "RS_2013-12": {"investing": 1413, "stocks": 692, "wallstreetbets": 148}, "RS_2024-05": {"wallstreetbets": 12056, "stocks": 925, "investing": 1136}, "RS_2008-04": {"investing": 15}, "RS_2019-02": {"stocks": 777, "investing": 1338, "wallstreetbets": 2219}, "RS_2008-03": {"investing": 28}, "RS_2024-02": {"wallstreetbets": 11568, "investing": 1312, "stocks": 1137}, "RS_2011-03": {"investing": 326, "stocks": 42}, "RS_2011-04": {"investing": 301, "stocks": 59}, "RS_2022-09": {"wallstreetbets": 9756, "stocks": 844, "investing": 525}, "RS_2013-07": {"investing": 1378, "stocks": 314, "wallstreetbets": 83}, "RS_2024-10": {"wallstreetbets": 6818, "stocks": 836, "investing": 1184}, "RS_2008-11": {"investing": 37, "stocks": 23}, "RS_2019-10": {"wallstreetbets": 2355, "investing": 1287, "stocks": 811}, "RS_2020-07": {"wallstreetbets": 7229, "stocks": 4192, "investing": 1055}, "RS_2017-10": {"stocks": 1153, "wallstreetbets": 3032, "investing": 1198}, "RS_2006-11": {}, "RS_2011-09": {"investing": 408, "stocks": 136}, "RS_2022-04": {"wallstreetbets": 8132, "investing": 534, "stocks": 1262}, "RS_2022-03": {"stocks": 1257, "wallstreetbets": 6841, "investing": 424}, "RS_2006-03": {}, "RS_2017-02": {"wallstreetbets": 2416, "investing": 1342, "stocks": 886}, "RS_2006-04": {}, "RS_2020-12": {"stocks": 3057, "wallstreetbets": 11900, "investing": 1272}, "RS_2017-05": {"wallstreetbets": 2331, "stocks": 851, "investing": 1224}, "RS_2024-08": {"wallstreetbets": 8418, "investing": 1270, "stocks": 1162}, "RS_2008-09": {"stocks": 17, "investing": 9}, "RS_2015-01": {"stocks": 571, "investing": 1855, "wallstreetbets": 283}, "RS_2019-08": {"stocks": 994, "wallstreetbets": 4653, "investing": 1641}, "RS_2022-11": {"wallstreetbets": 8656, "stocks": 619, "investing": 547}, "RS_2015-06": {"investing": 1413, "stocks": 512, "wallstreetbets": 809}, "RS_2018-05": {"wallstreetbets": 4260, "investing": 1197, "stocks": 848}, "RS_2025-05": {"wallstreetbets": 6921, "investing": 1075, "stocks": 1308}, "RS_2012-12": {"stocks": 177, "investing": 833, "wallstreetbets": 34}, "RS_2009-04": {"investing": 63, "stocks": 7}, "RS_2018-02": {"stocks": 980, "wallstreetbets": 4449, "investing": 1578}, "RS_2009-03": {"investing": 53, "stocks": 10}, "RS_2025-02": {"wallstreetbets": 6391, "investing": 1443, "stocks": 1198}, "RS_2010-11": {"investing": 161, "stocks": 19}, "RS_2016-08": {"stocks": 742, "wallstreetbets": 2853, "investing": 1127}, "RS_2007-09": {}, "RS_2023-09": {"wallstreetbets": 4878, "investing": 1073, "stocks": 758}, "RS_2012-07": {"investing": 833, "stocks": 154, "wallstreetbets": 86}, "RS_2009-11": {"investing": 64, "stocks": 10}, "RS_2018-10": {"stocks": 1203, "wallstreetbets": 5312, "investing": 1491}, "RS_2010-03": {"stocks": 47, "investing": 73}, "RS_2010-04": {"investing": 147, "stocks": 65}, "RS_2017-04": {"wallstreetbets": 2168, "investing": 1034, "stocks": 779}, "RS_2006-05": {}, "RS_2017-03": {"investing": 1303, "wallstreetbets": 2653, "stocks": 992}, "RS_2006-02": {}, "RS_2015-07": {"wallstreetbets": 1263, "investing": 1745, "stocks": 820}, "RS_2022-10": {"wallstreetbets": 12042, "stocks": 889, "investing": 481}, "RS_2019-09": {"wallstreetbets": 2517, "investing": 1195, "stocks": 695}, "RS_2008-08": {"stocks": 14, "investing": 9}, "RS_2024-09": {"investing": 1117, "wallstreetbets": 5586, "stocks": 752}, "RS_2011-08": {"investing": 552, "stocks": 173}, "RS_2020-01": {"stocks": 1513, "wallstreetbets": 4620, "investing": 1683}, "RS_2006-10": {}, "RS_2017-11": {"wallstreetbets": 2864, "stocks": 1124, "investing": 1353}, "RS_2020-06": {"wallstreetbets": 7843, "stocks": 4707, "investing": 1293}, "RS_2022-02": {"wallstreetbets": 5537, "stocks": 1258, "investing": 345}, "RS_2015-12": {"investing": 1214, "stocks": 405, "wallstreetbets": 1114}, "RS_2022-05": {"wallstreetbets": 8402, "stocks": 1448, "investing": 526}, "RS_2018-11": {"wallstreetbets": 3537, "stocks": 770, "investing": 1236}, "RS_2009-10": {"investing": 58, "stocks": 20}, "RS_2012-06": {"investing": 835, "wallstreetbets": 101, "stocks": 110}, "RS_2012-01": {"investing": 1010, "stocks": 358}, "RS_2023-08": {"stocks": 831, "wallstreetbets": 5897, "investing": 1063}, "RS_2010-05": {"investing": 203, "stocks": 63}, "RS_2010-02": {"stocks": 30, "investing": 58}, "RS_2025-03": {"wallstreetbets": 5291, "stocks": 1377, "investing": 1371}, "RS_2009-02": {"investing": 38, "stocks": 7}, "RS_2018-03": {"wallstreetbets": 4132, "stocks": 1021, "investing": 1548}, "RS_2009-05": {"investing": 43, "stocks": 19}, "RS_2025-04": {"stocks": 2330, "wallstreetbets": 9686, "investing": 1642}, "RS_2018-04": {"stocks": 725, "wallstreetbets": 3435, "investing": 1296}, "RS_2007-08": {}, "RS_2016-09": {"wallstreetbets": 2614, "investing": 931, "stocks": 691}, "RS_2010-10": {"investing": 159, "stocks": 14}, "RS_2015-02": {"investing": 1628, "stocks": 747, "wallstreetbets": 328}, "RS_2022-12": {"wallstreetbets": 7393, "investing": 591, "stocks": 637}, "RS_2015-05": {"stocks": 529, "wallstreetbets": 749, "investing": 1533}, "RS_2017-01": {"investing": 1340, "wallstreetbets": 2176, "stocks": 767}, "RS_2006-07": {}, "RS_2020-11": {"wallstreetbets": 12134, "investing": 873, "stocks": 2111}, "RS_2017-06": {"wallstreetbets": 2843, "investing": 1234, "stocks": 910}, "RS_2022-07": {"wallstreetbets": 7942, "investing": 381, "stocks": 834}, "RS_2015-10": {"wallstreetbets": 1224, "investing": 1292, "stocks": 525}, "RS_2013-09": {"investing": 1192, "stocks": 344, "wallstreetbets": 65}, "RS_2020-04": {"stocks": 5199, "wallstreetbets": 13243, "investing": 2798}, "RS_2006-12": {}, "RS_2020-03": {"wallstreetbets": 17358, "investing": 3453, "stocks": 4374}, "RS_2021-09": {"wallstreetbets": 9048, "stocks": 1044, "investing": 211}, "RS_2010-07": {"investing": 86, "stocks": 23}, "RS_2012-03": {"investing": 1377, "stocks": 114}, "RS_2012-04": {"investing": 1194, "stocks": 121, "wallstreetbets": 29}, "RS_2009-12": {"investing": 67, "stocks": 25}, "RS_2010-12": {"investing": 189, "stocks": 20}, "RS_2018-06": {"wallstreetbets": 5556, "stocks": 953, "investing": 1243}, "RS_2025-06": {"wallstreetbets": 5384, "investing": 966, "stocks": 1119}, "RS_2012-11": {"investing": 894, "stocks": 169, "wallstreetbets": 39}, "RS_2009-07": {"investing": 142, "stocks": 14}, "RS_2018-01": {"investing": 1814, "wallstreetbets": 3054, "stocks": 1204}, "RS_2005-09": {}, "RS_2025-01": {"wallstreetbets": 6948, "investing": 1763, "stocks": 1173}, "RS_2014-08": {"investing": 1699, "stocks": 620, "wallstreetbets": 101}, "RS_2013-08": {"investing": 1282, "stocks": 430, "wallstreetbets": 63}, "RS_2022-01": {"wallstreetbets": 11241, "stocks": 1618, "investing": 345}, "RS_2015-11": {"wallstreetbets": 1205, "investing": 1186, "stocks": 504}, "RS_2022-06": {"wallstreetbets": 7738, "stocks": 930, "investing": 389}, "RS_2020-02": {"investing": 2217, "wallstreetbets": 9175, "stocks": 2113}, "RS_2017-12": {"stocks": 866, "wallstreetbets": 2106, "investing": 1408}, "RS_2020-05": {"wallstreetbets": 9689, "stocks": 3962, "investing": 1692}, "RS_2015-04": {"investing": 1602, "wallstreetbets": 509, "stocks": 657}, "RS_2015-03": {"stocks": 690, "wallstreetbets": 437, "investing": 1624}, "RS_2017-07": {"wallstreetbets": 2447, "investing": 1344, "stocks": 898}, "RS_2020-10": {"wallstreetbets": 6693, "investing": 819, "stocks": 1814}, "RS_2006-06": {}, "RS_2006-01": {}, "RS_2014-09": {"stocks": 716, "investing": 1854, "wallstreetbets": 153}, "RS_2009-01": {"investing": 28, "stocks": 8}, "RS_2005-08": {}, "RS_2009-06": {"investing": 66, "stocks": 12}, "RS_2012-10": {"investing": 939, "stocks": 132, "wallstreetbets": 29}, "RS_2018-07": {"wallstreetbets": 5238, "investing": 1373, "stocks": 869}, "RS_2010-06": {"investing": 106, "stocks": 31}, "RS_2010-01": {"investing": 38, "stocks": 31}, "RS_2021-08": {"wallstreetbets": 8100, "stocks": 1242, "investing": 338}, "RS_2018-12": {"investing": 1598, "wallstreetbets": 4041, "stocks": 729}, "RS_2012-05": {"investing": 1301, "wallstreetbets": 171, "stocks": 140}, "RS_2012-02": {"investing": 1297, "stocks": 167}, "RS_2021-02": {"wallstreetbets": 121230, "stocks": 4138, "investing": 800}, "RS_2021-05": {"wallstreetbets": 16493, "stocks": 1553, "investing": 289}, "RS_2016-12": {"investing": 1252, "wallstreetbets": 1369, "stocks": 682}, "RS_2012-08": {"wallstreetbets": 78, "investing": 936, "stocks": 162}, "RS_2023-01": {"wallstreetbets": 7966, "stocks": 715, "investing": 674}, "RS_2023-06": {"investing": 684, "wallstreetbets": 4513, "stocks": 656}, "RS_2014-11": {"investing": 1463, "wallstreetbets": 157, "stocks": 768}, "RS_2005-10": {}, "RS_2021-10": {"wallstreetbets": 9377, "stocks": 1121, "investing": 278}, "RS_2016-07": {"wallstreetbets": 2679, "investing": 1132, "stocks": 757}, "RS_2007-06": {}, "RS_2007-01": {}, "RS_2014-04": {"investing": 1533, "stocks": 655, "wallstreetbets": 156}, "RS_2014-03": {"stocks": 978, "investing": 1771, "wallstreetbets": 267}, "RS_2015-09": {"wallstreetbets": 1078, "investing": 1251, "stocks": 438}, "RS_2008-01": {}, "RS_2008-06": {"investing": 5, "stocks": 2}, "RS_2024-07": {"investing": 1226, "wallstreetbets": 6767, "stocks": 1006}, "RS_2013-10": {"investing": 1524, "stocks": 469, "wallstreetbets": 69}, "RS_2019-07": {"investing": 1285, "stocks": 863, "wallstreetbets": 2733}, "RS_2019-12": {"wallstreetbets": 2647, "stocks": 957, "investing": 1551}, "RS_2024-12": {"stocks": 1081, "investing": 1603, "wallstreetbets": 6978}, "RS_2013-05": {"stocks": 290, "investing": 1459, "wallstreetbets": 77}, "RS_2013-02": {"investing": 1069, "wallstreetbets": 25, "stocks": 303}, "RS_2011-06": {"investing": 331, "stocks": 134}, "RS_2011-01": {"investing": 353, "stocks": 75}, "RS_2020-08": {"wallstreetbets": 7632, "stocks": 2825, "investing": 1123}, "RS_2016-01": {"investing": 1948, "wallstreetbets": 1510, "stocks": 701}, "RS_2007-07": {}, "RS_2016-06": {"wallstreetbets": 2209, "investing": 1295, "stocks": 734}, "RS_2021-11": {"wallstreetbets": 10095, "stocks": 1461, "investing": 350}, "RS_2014-02": {"stocks": 949, "wallstreetbets": 295, "investing": 1797}, "RS_2014-05": {"investing": 1408, "stocks": 415, "wallstreetbets": 163}, "RS_2023-12": {"wallstreetbets": 5576, "stocks": 970, "investing": 1155}, "RS_2021-04": {"wallstreetbets": 18630, "stocks": 1707, "investing": 244}, "RS_2007-12": {}, "RS_2021-03": {"wallstreetbets": 47295, "stocks": 2981, "investing": 374}, "RS_2005-11": {}, "RS_2014-10": {"investing": 1814, "stocks": 810, "wallstreetbets": 182}, "RS_2023-07": {"wallstreetbets": 5232, "investing": 1014, "stocks": 922}, "RS_2012-09": {"investing": 793, "wallstreetbets": 43, "stocks": 124}, "RS_2013-03": {"investing": 1073, "stocks": 279, "wallstreetbets": 39}, "RS_2013-04": {"investing": 1116, "wallstreetbets": 73, "stocks": 234}, "RS_2008-12": {"investing": 36, "stocks": 8}, "RS_2020-09": {"wallstreetbets": 8625, "stocks": 1896, "investing": 902}, "RS_2011-07": {"investing": 335, "stocks": 200}, "RS_2019-06": {"stocks": 793, "wallstreetbets": 2581, "investing": 1174}, "RS_2013-11": {"investing": 1426, "wallstreetbets": 101, "stocks": 612}, "RS_2024-06": {"stocks": 970, "investing": 1196, "wallstreetbets": 8698}, "RS_2008-07": {"stocks": 5, "investing": 2}, "RS_2019-01": {"investing": 1682, "stocks": 865, "wallstreetbets": 3496}, "RS_2024-01": {"investing": 1372, "wallstreetbets": 6933, "stocks": 1028}, "RS_2015-08": {"investing": 2008, "wallstreetbets": 1494, "stocks": 840}, "RS_2011-12": {"investing": 835, "stocks": 178}}